Classfile /C:/Users/Никита/Projects/m32/out/com/k381/Main.class
  Last modified 17 окт. 2018 г.; size 1181 bytes
  MD5 checksum 47689e7376bb063d8ad23b1f4485e11e
  Compiled from "Main.java"
public class com.k381.Main
  minor version: 0
  major version: 54
  flags: (0x0021) ACC_PUBLIC, ACC_SUPER
  this_class: #12                         // com/k381/Main
  super_class: #13                        // java/lang/Object
  interfaces: 0, fields: 0, methods: 3, attributes: 3
Constant pool:
   #1 = Methodref          #13.#24        // java/lang/Object."<init>":()V
   #2 = String             #25            // Sully
   #3 = Methodref          #26.#27        // com/google/common/collect/Lists.asList:(Ljava/lang/Object;[Ljava/lang/Object;)Ljava/util/List;
   #4 = Methodref          #13.#28        // java/lang/Object.toString:()Ljava/lang/String;
   #5 = Methodref          #12.#29        // com/k381/Main.test:(Ljava/lang/String;)V
   #6 = Fieldref           #30.#31        // java/lang/System.out:Ljava/io/PrintStream;
   #7 = String             #32            // agr_prop
   #8 = String             #33            // Tester
   #9 = Methodref          #30.#34        // java/lang/System.getProperty:(Ljava/lang/String;Ljava/lang/String;)Ljava/lang/String;
  #10 = InvokeDynamic      #0:#38         // #0:makeConcatWithConstants:(Ljava/lang/String;Ljava/lang/String;)Ljava/lang/String;
  #11 = Methodref          #39.#40        // java/io/PrintStream.println:(Ljava/lang/String;)V
  #12 = Class              #41            // com/k381/Main
  #13 = Class              #42            // java/lang/Object
  #14 = Utf8               <init>
  #15 = Utf8               ()V
  #16 = Utf8               Code
  #17 = Utf8               LineNumberTable
  #18 = Utf8               main
  #19 = Utf8               ([Ljava/lang/String;)V
  #20 = Utf8               test
  #21 = Utf8               (Ljava/lang/String;)V
  #22 = Utf8               SourceFile
  #23 = Utf8               Main.java
  #24 = NameAndType        #14:#15        // "<init>":()V
  #25 = Utf8               Sully
  #26 = Class              #43            // com/google/common/collect/Lists
  #27 = NameAndType        #44:#45        // asList:(Ljava/lang/Object;[Ljava/lang/Object;)Ljava/util/List;
  #28 = NameAndType        #46:#47        // toString:()Ljava/lang/String;
  #29 = NameAndType        #20:#21        // test:(Ljava/lang/String;)V
  #30 = Class              #48            // java/lang/System
  #31 = NameAndType        #49:#50        // out:Ljava/io/PrintStream;
  #32 = Utf8               agr_prop
  #33 = Utf8               Tester
  #34 = NameAndType        #51:#52        // getProperty:(Ljava/lang/String;Ljava/lang/String;)Ljava/lang/String;
  #35 = Utf8               BootstrapMethods
  #36 = MethodHandle       6:#53          // REF_invokeStatic java/lang/invoke/StringConcatFactory.makeConcatWithConstants:(Ljava/lang/invoke/MethodHandles$Lookup;Ljava/lang/String;Ljava/lang/invoke/MethodType;Ljava/lang/String;[Ljava/lang/Object;)Ljava/lang/invoke/CallSite;
  #37 = String             #54            // Hello \u0001!\n\u0001
  #38 = NameAndType        #55:#52        // makeConcatWithConstants:(Ljava/lang/String;Ljava/lang/String;)Ljava/lang/String;
  #39 = Class              #56            // java/io/PrintStream
  #40 = NameAndType        #57:#21        // println:(Ljava/lang/String;)V
  #41 = Utf8               com/k381/Main
  #42 = Utf8               java/lang/Object
  #43 = Utf8               com/google/common/collect/Lists
  #44 = Utf8               asList
  #45 = Utf8               (Ljava/lang/Object;[Ljava/lang/Object;)Ljava/util/List;
  #46 = Utf8               toString
  #47 = Utf8               ()Ljava/lang/String;
  #48 = Utf8               java/lang/System
  #49 = Utf8               out
  #50 = Utf8               Ljava/io/PrintStream;
  #51 = Utf8               getProperty
  #52 = Utf8               (Ljava/lang/String;Ljava/lang/String;)Ljava/lang/String;
  #53 = Methodref          #58.#59        // java/lang/invoke/StringConcatFactory.makeConcatWithConstants:(Ljava/lang/invoke/MethodHandles$Lookup;Ljava/lang/String;Ljava/lang/invoke/MethodType;Ljava/lang/String;[Ljava/lang/Object;)Ljava/lang/invoke/CallSite;
  #54 = Utf8               Hello \u0001!\n\u0001
  #55 = Utf8               makeConcatWithConstants
  #56 = Utf8               java/io/PrintStream
  #57 = Utf8               println
  #58 = Class              #60            // java/lang/invoke/StringConcatFactory
  #59 = NameAndType        #55:#64        // makeConcatWithConstants:(Ljava/lang/invoke/MethodHandles$Lookup;Ljava/lang/String;Ljava/lang/invoke/MethodType;Ljava/lang/String;[Ljava/lang/Object;)Ljava/lang/invoke/CallSite;
  #60 = Utf8               java/lang/invoke/StringConcatFactory
  #61 = Class              #66            // java/lang/invoke/MethodHandles$Lookup
  #62 = Utf8               Lookup
  #63 = Utf8               InnerClasses
  #64 = Utf8               (Ljava/lang/invoke/MethodHandles$Lookup;Ljava/lang/String;Ljava/lang/invoke/MethodType;Ljava/lang/String;[Ljava/lang/Object;)Ljava/lang/invoke/CallSite;
  #65 = Class              #67            // java/lang/invoke/MethodHandles
  #66 = Utf8               java/lang/invoke/MethodHandles$Lookup
  #67 = Utf8               java/lang/invoke/MethodHandles
{
  public com.k381.Main();
    descriptor: ()V
    flags: (0x0001) ACC_PUBLIC
    Code:
      stack=1, locals=1, args_size=1
         0: aload_0
         1: invokespecial #1                  // Method java/lang/Object."<init>":()V
         4: return
      LineNumberTable:
        line 5: 0

  public static void main(java.lang.String[]);
    descriptor: ([Ljava/lang/String;)V
    flags: (0x0009) ACC_PUBLIC, ACC_STATIC
    Code:
      stack=2, locals=1, args_size=1
         0: ldc           #2                  // String Sully
         2: aload_0
         3: invokestatic  #3                  // Method com/google/common/collect/Lists.asList:(Ljava/lang/Object;[Ljava/lang/Object;)Ljava/util/List;
         6: invokevirtual #4                  // Method java/lang/Object.toString:()Ljava/lang/String;
         9: invokestatic  #5                  // Method test:(Ljava/lang/String;)V
        12: return
      LineNumberTable:
        line 8: 0
        line 9: 12
}
SourceFile: "Main.java"
InnerClasses:
  public static final #62= #61 of #65;    // Lookup=class java/lang/invoke/MethodHandles$Lookup of class java/lang/invoke/MethodHandles
BootstrapMethods:
  0: #36 REF_invokeStatic java/lang/invoke/StringConcatFactory.makeConcatWithConstants:(Ljava/lang/invoke/MethodHandles$Lookup;Ljava/lang/String;Ljava/lang/invoke/MethodType;Ljava/lang/String;[Ljava/lang/Object;)Ljava/lang/invoke/CallSite;
    Method arguments:
      #37 Hello \u0001!\n\u0001
